dev_test/__init__.py
dev_test/_modidx.py
dev_test/core.py
dev_test-0.0.1.dist-info/LICENSE
dev_test-0.0.1.dist-info/METADATA
dev_test-0.0.1.dist-info/WHEEL
dev_test-0.0.1.dist-info/entry_points.txt
dev_test-0.0.1.dist-info/top_level.txt
dev_test-0.0.1.dist-info/RECORD
